{
  "$schema": "https://json.schemastore.org/tsconfig",
  "extends": "./base.json",
  "compilerOptions": {
    "module": "CommonJS",
    "esModuleInterop": true,
    "declaration": true,
    "removeComments": true,
    "emitDecoratorMetadata": true,
    "experimentalDecorators": true,
    "allowSyntheticDefaultImports": true,
    "outDir": "./dist",
    "sourceMap": true,
    "incremental": true,
    "skipLibCheck": true,
    "strictNullChecks": false,
    "noImplicitAny": false,
    "strictBindCallApply": false,
    "strict": false,
    "forceConsistentCasingInFileNames": false,
    "noFallthroughCasesInSwitch": false
  }
}
